epicure/Utils.py
epicure/__init__.py
epicure/_version.py
epicure/concatenate_movie.py
epicure/displaying.py
epicure/editing.py
epicure/epicuring.py
epicure/epiwidgets.py
epicure/inspecting.py
epicure/laptrack_centroids.py
epicure/laptrack_overlaps.py
epicure/napari.yaml
epicure/outputing.py
epicure/preferences.py
epicure/start_epicuring.py
epicure/tracking.py
epicure/trackmate_export.py
epicure-1.3.dist-info/LICENSE
epicure-1.3.dist-info/METADATA
epicure-1.3.dist-info/WHEEL
epicure-1.3.dist-info/entry_points.txt
epicure-1.3.dist-info/top_level.txt
epicure-1.3.dist-info/RECORD
