Metadata-Version: 2.1
Name: epicure
Version: 1.3
Summary: Napari plugin to manually correct epithelia segmentation in movies
Author: Gaëlle Letort
License: BSD 3-Clause License
Project-URL: Bug Tracker, https://github.com/gletort/Epicure/issues
Project-URL: Documentation, https://gletort.github.io/Epicure/
Project-URL: Source Code, https://github.com/gletort/Epicure
Project-URL: User Support, https://github.com/gletort/Epicure/issues
Classifier: Framework :: napari
Classifier: Operating System :: OS Independent
Classifier: Programming Language :: Python
Classifier: Programming Language :: Python :: 3.9
Classifier: Programming Language :: Python :: 3.10
Classifier: Programming Language :: Python :: 3.11
Classifier: Topic :: Scientific/Engineering :: Image Processing
Requires-Python: >=3.9
License-File: LICENSE
Requires-Dist: napari<=0.6.4
Requires-Dist: numpy
Requires-Dist: qtpy
Requires-Dist: bioio
Requires-Dist: bioio-bioformats
Requires-Dist: bioio-tifffile
Requires-Dist: scikit-image
Requires-Dist: opencv-python-headless
Requires-Dist: roifile
Requires-Dist: pyqtwebengine
Requires-Dist: magicgui
Requires-Dist: scipy
Requires-Dist: xlsxwriter
Requires-Dist: plotly
Requires-Dist: kaleido
Requires-Dist: imagecodecs
Requires-Dist: edt
Requires-Dist: packaging
Requires-Dist: laptrack
Requires-Dist: joblib
